xidauth/__init__.py
xidauth/auth_pb2.py
xidauth/credentials.py
xidauth/delegation.py
xidauth/abi/XayaAccounts.json
xidauth/abi/XayaDelegation.json
xidauth/abi/__init__.py
xidauth/tests/credentials.py
xidauth/tests/delegation.py
xidauth-1.0.0.dist-info/licenses/AUTHORS
xidauth-1.0.0.dist-info/licenses/COPYING
xidauth-1.0.0.dist-info/METADATA
xidauth-1.0.0.dist-info/WHEEL
xidauth-1.0.0.dist-info/top_level.txt
xidauth-1.0.0.dist-info/RECORD
