Metadata-Version: 2.4
Name: xidauth
Version: 1.0.0
Summary: Xid credentials verification based on delegation-contract
Author-email: Daniel Kraft <d@domob.eu>
License: The MIT License (MIT)
Project-URL: Homepage, https://xaya.io
Project-URL: Repository, https://github.com/xaya/xid
Classifier: Programming Language :: Python :: 3
Classifier: Operating System :: OS Independent
Classifier: License :: OSI Approved :: MIT License
Requires-Python: >=3.9
License-File: COPYING
License-File: AUTHORS
Requires-Dist: eth_account
Requires-Dist: jsonrpclib-pelix
Requires-Dist: protobuf
Requires-Dist: web3==7
Dynamic: license-file
